{
  "appId": "space.doki.modmanager-china",
  "productName": "Doki Doki Mod Manager 中国",
  "artifactName": "ddmm-cn-${version}-${os}-${arch}.${ext}",
  "files": [
    "!**/*.ts",
    "!**/*.map",
    "!**/*.rpy"
  ],
  "extraFiles": [
    "ui/**/*.*"
  ],
  "extraMetadata": {
    "description": "中国用户的Doki Doki Mod Manager版本",
    "name": "doki-doki-mod-manager-cn"
  },
  "protocols": [
    {
      "name": "Doki Doki Mod Manager",
      "schemes": [
        "ddmm"
      ]
    }
  ],
  "publish": [
    {
      "provider": "github",
      "repo": "DDMM-China",
      "owner": "DokiDokiModManager"
    }
  ],
  "win": {
    "target": [
      {
        "target": "nsis",
        "arch": [
          "x64",
          "ia32"
        ]
      }
    ]
  },
  "linux": {
    "category": "Game",
    "maintainer": "zudo@doki.space",
    "synopsis": "Doki Doki Mod Manager",
    "target": [
      "AppImage",
      "tar.gz"
    ],
    "publish": [
      "github"
    ]
  },
  "nsis": {
    "language": 2052
  },
  "mac": {
    "category": "public.app-category.games",
    "icon": "build/icon.icns",
    "target": [
      "dmg",
      "zip"
    ]
  }
}
